adept_ai/__init__.py
adept_ai/agent_builder.py
adept_ai/tool.py
adept_ai/utils.py
adept_ai/capabilities/__init__.py
adept_ai/capabilities/base.py
adept_ai/capabilities/composio.py
adept_ai/capabilities/function.py
adept_ai/capabilities/filesystem/__init__.py
adept_ai/capabilities/filesystem/directory_tree.py
adept_ai/capabilities/filesystem/main.py
adept_ai/capabilities/mcp/__init__.py
adept_ai/capabilities/mcp/client_session.py
adept_ai/capabilities/mcp/lifecycle_manager.py
adept_ai/capabilities/mcp/main.py
adept_ai/compat/__init__.py
adept_ai/compat/langchain.py
adept_ai/compat/openai.py
adept_ai/compat/pydantic_ai.py
adept_ai-0.2.3.dist-info/METADATA
adept_ai-0.2.3.dist-info/WHEEL
adept_ai-0.2.3.dist-info/top_level.txt
adept_ai-0.2.3.dist-info/RECORD
