Metadata-Version: 2.4
Name: adept_ai
Version: 0.2.3
Summary: Framework for creating dynamic AI agents with access to broad range of capabilities.
Author-email: Finn Andersen <finndersen@gmail.com>
License: MIT
Project-URL: Homepage, https://github.com/yourusername/your-repo
Project-URL: Documentation, https://your-docs-site
Project-URL: Source, https://github.com/yourusername/your-repo
Requires-Python: >=3.11
Requires-Dist: pydantic
Requires-Dist: pydantic-ai-slim[logfire]~=0.2.6
Requires-Dist: rich
Requires-Dist: python-dotenv
Requires-Dist: aiofiles
Requires-Dist: jinja2~=3.1.6
Requires-Dist: decorator~=5.2.1
Requires-Dist: mcp[cli]~=1.8.0
Provides-Extra: dev
Requires-Dist: pytest; extra == "dev"
Requires-Dist: ruff; extra == "dev"
Requires-Dist: pyright; extra == "dev"
Requires-Dist: pytest-asyncio>=0.26.0; extra == "dev"
Requires-Dist: twine; extra == "dev"
Provides-Extra: langchain
Requires-Dist: langchain~=0.3.25; extra == "langchain"
Requires-Dist: langgraph~=0.4.1; extra == "langchain"
Requires-Dist: langchain-google-genai~=2.1.4; extra == "langchain"
Requires-Dist: langchain-anthropic~=0.3.13; extra == "langchain"
Requires-Dist: langchain-openai~=0.3.17; extra == "langchain"
Provides-Extra: openai
Requires-Dist: openai~=1.0.0; extra == "openai"
Provides-Extra: pydantic-ai
Requires-Dist: pydantic-ai[logfire]~=0.1.9; extra == "pydantic-ai"
Provides-Extra: composio
Requires-Dist: composio-core~=0.7.16; extra == "composio"
Requires-Dist: composio-openai; extra == "composio"
